how_are_we_stranded_here/__init__.py
how_are_we_stranded_here/_version.py
how_are_we_stranded_here/check_strandedness.py
how_are_we_stranded_here/gff32gtf.py
how_are_we_stranded_here/gtf2bed.py
how_are_we_stranded_here/tests/__init__.py
how_are_we_stranded_here/tests/conftest.py
how_are_we_stranded_here/tests/test_examples.py
how_are_we_stranded_here-1.0.1.dist-info/AUTHORS.rst
how_are_we_stranded_here-1.0.1.dist-info/LICENSE
how_are_we_stranded_here-1.0.1.dist-info/METADATA
how_are_we_stranded_here-1.0.1.dist-info/WHEEL
how_are_we_stranded_here-1.0.1.dist-info/entry_points.txt
how_are_we_stranded_here-1.0.1.dist-info/top_level.txt
how_are_we_stranded_here-1.0.1.dist-info/RECORD
