Metadata-Version: 2.1
Name: how-are-we-stranded-here
Version: 1.0.1
Summary: Python package for testing strandedness of RNA-Seq fastq files
Home-page: https://github.com/betsig/how_are_we_stranded_here
Author: Beth Signal
Author-email: beth.signal@gmail.com
License: MIT
Platform: UNKNOWN
Classifier: Development Status :: 5 - Production/Stable
Classifier: Natural Language :: English
Classifier: Programming Language :: Python :: 3
Requires-Python: >=3.6
Requires-Dist: numpy
Requires-Dist: pandas
Requires-Dist: RSeQC
